{".class": "MypyFile", "_fullname": "srmnet.train", "is_partial_stub_package": false, "is_stub": false, "names": {".class": "SymbolTable", "BatchIterator": {".class": "SymbolTableNode", "cross_ref": "srmnet.data.BatchIterator", "kind": "Gdef"}, "DataIterator": {".class": "SymbolTableNode", "cross_ref": "srmnet.data.DataIterator", "kind": "Gdef"}, "Loss": {".class": "SymbolTableNode", "cross_ref": "srmnet.loss.Loss", "kind": "Gdef"}, "MSE": {".class": "SymbolTableNode", "cross_ref": "srmnet.loss.MSE", "kind": "Gdef"}, "NeuralNet": {".class": "SymbolTableNode", "cross_ref": "srmnet.nn.NeuralNet", "kind": "Gdef"}, "Optimizer": {".class": "SymbolTableNode", "cross_ref": "srmnet.optim.Optimizer", "kind": "Gdef"}, "SGD": {".class": "SymbolTableNode", "cross_ref": "srmnet.optim.SGD", "kind": "Gdef"}, "Tensor": {".class": "SymbolTableNode", "cross_ref": "srmnet.tensor.Tensor", "kind": "Gdef"}, "__doc__": {".class": "SymbolTableNode", "kind": "Gdef", "node": {".class": "Var", "flags": [], "fullname": "srmnet.train.__doc__", "name": "__doc__", "type": "builtins.str"}}, "__file__": {".class": "SymbolTableNode", "kind": "Gdef", "node": {".class": "Var", "flags": [], "fullname": "srmnet.train.__file__", "name": "__file__", "type": "builtins.str"}}, "__name__": {".class": "SymbolTableNode", "kind": "Gdef", "node": {".class": "Var", "flags": [], "fullname": "srmnet.train.__name__", "name": "__name__", "type": "builtins.str"}}, "__package__": {".class": "SymbolTableNode", "kind": "Gdef", "node": {".class": "Var", "flags": [], "fullname": "srmnet.train.__package__", "name": "__package__", "type": "builtins.str"}}, "train": {".class": "SymbolTableNode", "kind": "Gdef", "node": {".class": "FuncDef", "arg_kinds": [0, 0, 0, 1, 1, 1, 1], "arg_names": ["net", "inputs", "targets", "num_epochs", "iterator", "loss", "optimizer"], "flags": [], "fullname": "srmnet.train.train", "name": "train", "type": {".class": "CallableType", "arg_kinds": [0, 0, 0, 1, 1, 1, 1], "arg_names": ["net", "inputs", "targets", "num_epochs", "iterator", "loss", "optimizer"], "arg_types": ["srmnet.nn.NeuralNet", {".class": "AnyType", "missing_import_name": "srmnet.tensor.Tensor", "source_any": null, "type_of_any": 3}, {".class": "AnyType", "missing_import_name": "srmnet.tensor.Tensor", "source_any": null, "type_of_any": 3}, "builtins.int", "srmnet.data.DataIterator", "srmnet.loss.Loss", "srmnet.optim.Optimizer"], "bound_args": [], "def_extras": {"first_arg": null}, "fallback": "builtins.function", "implicit": false, "is_ellipsis_args": false, "name": "train", "ret_type": {".class": "NoneTyp"}, "variables": []}}}}, "path": "srmnet/train.py"}